setup.cfg
setup.py
QtPDFPrinter.egg-info/PKG-INFO
QtPDFPrinter.egg-info/SOURCES.txt
QtPDFPrinter.egg-info/dependency_links.txt
QtPDFPrinter.egg-info/requires.txt
QtPDFPrinter.egg-info/top_level.txt
qtpdfprinter/__init__.py
qtpdfprinter/command_handler.py
qtpdfprinter/converter.py
qtpdfprinter/templating.py