Metadata-Version: 1.1
Name: QtPDFPrinter
Version: 1.0a1
Summary: Creates PDFs from HTML or Jinja2 Templates using PySide
Home-page: https://github.com/jepayne1138/QtPDFPrinter
Author: James Payne
Author-email: jepayne1138@gmail.com
License: MIT
Download-URL: https://github.com/jepayne1138/QtPDFPrinter/tarball/1.0a1
Keywords: html pyside html convert pdf jinja
Platform: UNKNOWN
